verilog_src/delayer.v
/* Generated by Yosys 0.8+     369 (git sha1 ea0e0722, clang 10.0.1 -fPIC -Os) */

(* \nmigen.hierarchy  = "top" *)
(* top =  1  *)
(* generator = "nMigen" *)
module top(rst, clk, out_sig, in_sig);
  wire [3:0] \$1 ;
  wire [3:0] \$2 ;
  wire \$4 ;
  wire \$6 ;
  (* src = "./migen_src/delayer.py:12" *)
  reg \$next\out_sig ;
  (* src = "./migen_src/delayer.py:20" *)
  reg \$next\out_val ;
  (* src = "./migen_src/delayer.py:13" *)
  reg [2:0] \$next\timer ;
  (* src = "./migen_src/delayer.py:19" *)
  reg \$next\timer_start ;
  (* src = "/anaconda3/envs/py36/lib/python3.6/site-packages/nmigen/hdl/ir.py:329" *)
  input clk;
  (* src = "./migen_src/delayer.py:11" *)
  input in_sig;
  (* src = "./migen_src/delayer.py:12" *)
  output out_sig;
  (* init = 1'h0 *)
  (* src = "./migen_src/delayer.py:20" *)
  reg out_val = 1'h0;
  (* src = "/anaconda3/envs/py36/lib/python3.6/site-packages/nmigen/hdl/ir.py:329" *)
  input rst;
  (* init = 3'h6 *)
  (* src = "./migen_src/delayer.py:13" *)
  reg [2:0] timer = 3'h6;
  (* init = 1'h0 *)
  (* src = "./migen_src/delayer.py:19" *)
  reg timer_start = 1'h0;
  assign \$2  = timer - (* src = "./migen_src/delayer.py:28" *) 1'h1;
  assign \$4  = timer == (* src = "./migen_src/delayer.py:30" *) 1'h0;
  assign \$6  = \$4  | (* src = "./migen_src/delayer.py:30" *) out_val;
  always @(posedge clk)
      out_val <= \$next\out_val ;
  always @(posedge clk)
      timer <= \$next\timer ;
  always @(posedge clk)
      timer_start <= \$next\timer_start ;
  always @* begin
    \$next\timer_start  = timer_start;
    casez (in_sig)
      1'h1:
          \$next\timer_start  = 1'h1;
    endcase
    casez (rst)
      1'h1:
          \$next\timer_start  = 1'h0;
    endcase
  end
  always @* begin
    \$next\timer  = timer;
    casez (timer_start)
      1'h1:
          \$next\timer  = \$1 [2:0];
    endcase
    casez (rst)
      1'h1:
          \$next\timer  = 3'h6;
    endcase
  end
  always @* begin
    \$next\out_val  = out_val;
    \$next\out_val  = \$6 ;
    casez (rst)
      1'h1:
          \$next\out_val  = 1'h0;
    endcase
  end
  always @* begin
    \$next\out_sig  = 1'h0;
    \$next\out_sig  = out_val;
  end
  assign \$1  = \$2 ;
  assign out_sig = \$next\out_sig ;
endmodule

simulations/delayer_test_1.vcd
$comment Generated by nMigen $end
$date 2019-06-06 02:19:33.363570 $end
$timescale 100 ps $end
$scope module top $end
$var wire 1 0 in_sig $end
$var wire 1 1 rst $end
$var wire 1 2 clk $end
$var wire 1 3 timer_start $end
$var wire 3 4 timer $end
$var wire 1 5 out_val $end
$var wire 1 6 out_sig $end
$upscope $end
$enddefinitions $end
#0
$dumpvars
00
01
02
03
b110 4
05
06
$end
#50
12
#51
10
#100
02
#150
12
#151
13
#200
02
#249
12
#251
b101 4
#299
02
#349
12
#350
b100 4
#399
02
#449
12
#450
b11 4
#499
02
#549
12
#550
b10 4
#599
02
#650
12
b1 4
#700
02
#750
12
#751
b0 4
#800
02
#850
12
#851
b111 4
15
16
#900
02
#950
12
#951
b110 4
#1000
02
#1050
12
#1051
b101 4
#1100
02
#1150
12
#1151
b100 4
#1200
02
#1250
12
#1251
b11 4
#1300
02
#1350
12
#1351
b10 4
#1400
02
#1450
12
#1451
b1 4
#1500
02
#1550
12
#1551
b0 4
#1600
02
#1650
12
#1651
b111 4
#1700
02
#1750
12
#1751
b110 4
#1800
02
#1850
12
#1851
b101 4
#1900
02
#1950
12
#1951
b100 4
